restapi_logging_handler
