Metadata-Version: 1.1
Name: restapi-logging-handler
Version: 0.1.10
Summary: A handler for the python logging module that sends logs         through any REST-ful API. Fully asyncronous. With Loggly support.
Home-page: https://github.com/narwhaljames/restapi-logging-handler.git
Author: RJ Gilligan
Author-email: rj.gilligan@nrgnergy.com
License: MIT
Download-URL: https://github.com/narwhaljames/restapi-logging-handler/tarball/0.1.10
Keywords: rest,api,logging,handler,loggly
Platform: UNKNOWN
